README.md
setup.py
smallcloud/__init__.py
smallcloud/__main__.py
smallcloud/call_api.py
smallcloud/code_root.py
smallcloud/config.py
smallcloud/inference_client.py
smallcloud/inference_server.py
smallcloud/launch.py
smallcloud/ssh_commands.py
smallcloud.egg-info/PKG-INFO
smallcloud.egg-info/SOURCES.txt
smallcloud.egg-info/dependency_links.txt
smallcloud.egg-info/entry_points.txt
smallcloud.egg-info/requires.txt
smallcloud.egg-info/top_level.txt