Metadata-Version: 1.1
Name: smallcloud
Version: 0.2.4
Summary: Run your GPU-intensive tasks using this command line tool / Python library
Home-page: https://github.com/smallcloudai/smallcloud
Author: Small Magellanic Cloud AI Ltd.
Author-email: cli-tool@smallcloud.tech
License: GNU GPLv3
Platform: UNKNOWN
Classifier: Development Status :: 3 - Alpha
Classifier: Topic :: Scientific/Engineering :: Artificial Intelligence
Classifier: Intended Audience :: Developers
Classifier: License :: OSI Approved :: GNU General Public License v3 (GPLv3)
Classifier: Environment :: Console
Classifier: Operating System :: OS Independent
